odoo/addons/currency_rate_update_cmc/README.rst
odoo/addons/currency_rate_update_cmc/__init__.py
odoo/addons/currency_rate_update_cmc/__manifest__.py
odoo/addons/currency_rate_update_cmc/i18n/currency_rate_update_cmc.pot
odoo/addons/currency_rate_update_cmc/i18n/es.po
odoo/addons/currency_rate_update_cmc/i18n/fr.po
odoo/addons/currency_rate_update_cmc/i18n/it.po
odoo/addons/currency_rate_update_cmc/models/__init__.py
odoo/addons/currency_rate_update_cmc/models/res_currency_rate_provider_CMC.py
odoo/addons/currency_rate_update_cmc/readme/CONFIGURE.rst
odoo/addons/currency_rate_update_cmc/readme/CONTRIBUTORS.rst
odoo/addons/currency_rate_update_cmc/readme/DESCRIPTION.rst
odoo/addons/currency_rate_update_cmc/readme/INSTALL.rst
odoo/addons/currency_rate_update_cmc/static/description/icon.png
odoo/addons/currency_rate_update_cmc/static/description/index.html
odoo/addons/currency_rate_update_cmc/wizards/res_currency_rate_update_wizard.xml
odoo14_addon_currency_rate_update_cmc-14.0.1.0.1.dev11.dist-info/METADATA
odoo14_addon_currency_rate_update_cmc-14.0.1.0.1.dev11.dist-info/WHEEL
odoo14_addon_currency_rate_update_cmc-14.0.1.0.1.dev11.dist-info/top_level.txt
odoo14_addon_currency_rate_update_cmc-14.0.1.0.1.dev11.dist-info/RECORD
